brood/__init__.py
brood/__main__.py
brood/command.py
brood/config.py
brood/constants.py
brood/errors.py
brood/executor.py
brood/fanout.py
brood/main.py
brood/message.py
brood/monitor.py
brood/py.typed
brood/renderer.py
brood/utils.py
brood/watch.py
brood-0.2.0.dist-info/entry_points.txt
brood-0.2.0.dist-info/LICENSE
brood-0.2.0.dist-info/WHEEL
brood-0.2.0.dist-info/METADATA
brood-0.2.0.dist-info/RECORD
